ebfe/__init__.py
ebfe/app.py
ebfe/cmd_line.py
ebfe/old_tui.py
ebfe/tui.py
ebfe/tui_curses.py
ebfe-0.0.6.dist-info/LICENSE
ebfe-0.0.6.dist-info/METADATA
ebfe-0.0.6.dist-info/WHEEL
ebfe-0.0.6.dist-info/entry_points.txt
ebfe-0.0.6.dist-info/top_level.txt
ebfe-0.0.6.dist-info/RECORD
