Metadata-Version: 2.1
Name: ebfe
Version: 0.0.6
Summary: EBFE Binary File Editor
Home-page: https://gitlab.com/icostin/ebfe-py
Author: Costin Ionescu, Dumitru Stama
Author-email: costin.ionescu@gmail.com, dumitru.stama@gmail.com
License: MIT
Platform: UNKNOWN
Requires-Dist: configparser
Requires-Dist: zlx (>=0.0.12)
